allmark/__init__.py
allmark/__main__.py
allmark/analyzers.py
allmark/cleaners.py
allmark/cli.py
allmark/converter.py
allmark/ocr.py
allmark/patterns.py
allmark/pdf_extract.py
allmark/tokenizer.py
allmark/utils.py
allmark-0.6.0.dist-info/licenses/LICENSE
allmark-0.6.0.dist-info/METADATA
allmark-0.6.0.dist-info/WHEEL
allmark-0.6.0.dist-info/entry_points.txt
allmark-0.6.0.dist-info/top_level.txt
allmark-0.6.0.dist-info/RECORD
