Metadata-Version: 2.4
Name: allmark
Version: 0.6.0
Summary: Universal eBook → Markdown converter and cleaner
Author-email: David Condrey <davidcondrey@protonmail.com>
License: MIT
Project-URL: Homepage, https://github.com/dcondrey/allmark
Project-URL: Bug Tracker, https://github.com/dcondrey/allmark/issues
Project-URL: Repository, https://github.com/dcondrey/allmark
Classifier: Programming Language :: Python :: 3
Classifier: Programming Language :: Python :: 3.7
Classifier: Programming Language :: Python :: 3.8
Classifier: Programming Language :: Python :: 3.9
Classifier: Programming Language :: Python :: 3.10
Classifier: Programming Language :: Python :: 3.11
Classifier: License :: OSI Approved :: MIT License
Classifier: Operating System :: OS Independent
Classifier: Development Status :: 4 - Beta
Classifier: Intended Audience :: Developers
Classifier: Intended Audience :: End Users/Desktop
Classifier: Topic :: Text Processing :: Markup :: Markdown
Classifier: Topic :: Utilities
Requires-Python: >=3.7
License-File: LICENSE
Provides-Extra: dev
Requires-Dist: pytest<9.0,>=7.0; extra == "dev"
Requires-Dist: black<25.0,>=22.0; extra == "dev"
Requires-Dist: flake8<8.0,>=4.0; extra == "dev"
Requires-Dist: mypy<2.0,>=1.0; extra == "dev"
Dynamic: license-file
